{
  "_class": "shapePath",
  "booleanOperation": -1,
  "do_objectID": "D97C1A1C-B6EF-4455-A560-761762D6A210",
  "edited": true,
  "exportOptions": {
    "_class": "exportOptions",
    "exportFormats": [
    ],
    "includedLayerIds": [
    ],
    "layerOptions": 0,
    "shouldTrim": false
  },
  "frame": {
    "_class": "rect",
    "constrainProportions": false,
    "height": 14.84061153740749,
    "width": 8.48921855921857,
    "x": 0,
    "y": 0
  },
  "isFlippedHorizontal": false,
  "isFlippedVertical": false,
  "isLocked": false,
  "isVisible": true,
  "layerListExpandedType": 0,
  "name": "Path",
  "nameIsFixed": false,
  "path": {
    "_class": "path",
    "isClosed": true,
    "pointRadiusBehaviour": 1,
    "points": [
      {
        "_class": "curvePoint",
        "cornerRadius": 0,
        "curveFrom": "{0.99659411420360844, 0}",
        "curveMode": 1,
        "curveTo": "{0.99659411420360844, 0}",
        "hasCurveFrom": false,
        "hasCurveTo": false,
        "point": "{0.99659411420360844, 0}"
      },
      {
        "_class": "curvePoint",
        "cornerRadius": 0,
        "curveFrom": "{1, 0.67685824441854214}",
        "curveMode": 1,
        "curveTo": "{1, 0.67685824441854214}",
        "hasCurveFrom": false,
        "hasCurveTo": false,
        "point": "{1, 0.67685824441854214}"
      },
      {
        "_class": "curvePoint",
        "cornerRadius": 0,
        "curveFrom": "{0.003459102761961149, 1}",
        "curveMode": 1,
        "curveTo": "{0.003459102761961149, 1}",
        "hasCurveFrom": false,
        "hasCurveTo": false,
        "point": "{0.003459102761961149, 1}"
      },
      {
        "_class": "curvePoint",
        "cornerRadius": 0,
        "curveFrom": "{0, 0.32317164290624351}",
        "curveMode": 1,
        "curveTo": "{0, 0.32317164290624351}",
        "hasCurveFrom": false,
        "hasCurveTo": false,
        "point": "{0, 0.32317164290624351}"
      }
    ]
  },
  "resizingConstraint": 63,
  "resizingType": 0,
  "rotation": 0,
  "shouldBreakMaskChain": false
}