{
  "_class": "shapePath",
  "booleanOperation": -1,
  "do_objectID": "45B5C226-6311-4645-8F1A-56FDE2C5AA7F",
  "edited": true,
  "exportOptions": {
    "_class": "exportOptions",
    "exportFormats": [
    ],
    "includedLayerIds": [
    ],
    "layerOptions": 0,
    "shouldTrim": false
  },
  "frame": {
    "_class": "rect",
    "constrainProportions": false,
    "height": 16.56410256410257,
    "width": 3.586206896551738,
    "x": 0,
    "y": 0
  },
  "isFlippedHorizontal": false,
  "isFlippedVertical": false,
  "isLocked": false,
  "isVisible": true,
  "layerListExpandedType": 0,
  "name": "Path",
  "nameIsFixed": false,
  "path": {
    "_class": "path",
    "isClosed": true,
    "pointRadiusBehaviour": 1,
    "points": [
      {
        "_class": "curvePoint",
        "cornerRadius": 0,
        "curveFrom": "{0, 0.87561536815068497}",
        "curveMode": 1,
        "curveTo": "{0, 0.87561536815068497}",
        "hasCurveFrom": false,
        "hasCurveTo": false,
        "point": "{0, 0.87561536815068497}"
      },
      {
        "_class": "curvePoint",
        "cornerRadius": 0,
        "curveFrom": "{0.98858335379327233, 1}",
        "curveMode": 1,
        "curveTo": "{0.98858335379327233, 1}",
        "hasCurveFrom": false,
        "hasCurveTo": false,
        "point": "{0.98858335379327233, 1}"
      },
      {
        "_class": "curvePoint",
        "cornerRadius": 0,
        "curveFrom": "{1, 0.12441138698630151}",
        "curveMode": 1,
        "curveTo": "{1, 0.12441138698630151}",
        "hasCurveFrom": false,
        "hasCurveTo": false,
        "point": "{1, 0.12441138698630151}"
      },
      {
        "_class": "curvePoint",
        "cornerRadius": 0,
        "curveFrom": "{0.01141664620672766, 0}",
        "curveMode": 1,
        "curveTo": "{0.01141664620672766, 0}",
        "hasCurveFrom": false,
        "hasCurveTo": false,
        "point": "{0.01141664620672766, 0}"
      }
    ]
  },
  "resizingConstraint": 63,
  "resizingType": 0,
  "rotation": 0,
  "shouldBreakMaskChain": false
}