{
  "_class": "bitmap",
  "clippingMask": "{{0, 0}, {1, 1}}",
  "do_objectID": "C613D3FF-3668-4611-B3FF-0DFB21D64BD6",
  "exportOptions": {
    "_class": "exportOptions",
    "exportFormats": [
    ],
    "includedLayerIds": [
    ],
    "layerOptions": 0,
    "shouldTrim": false
  },
  "fillReplacesImage": false,
  "frame": {
    "_class": "rect",
    "constrainProportions": true,
    "height": 315,
    "width": 472.2693997071742,
    "x": -6.134699853587108,
    "y": 0
  },
  "image": {
    "_class": "MSJSONFileReference",
    "_ref": "images/2b2fc27b2da519a65445f89bf03c0406fb3db976.png",
    "_ref_class": "MSImageData"
  },
  "intendedDPI": 0,
  "isFlippedHorizontal": false,
  "isFlippedVertical": false,
  "isLocked": false,
  "isVisible": true,
  "layerListExpandedType": 0,
  "name": "164176365",
  "nameIsFixed": false,
  "resizingConstraint": 63,
  "resizingType": 0,
  "rotation": 0,
  "shouldBreakMaskChain": false,
  "style": {
    "_class": "style",
    "endDecorationType": 0,
    "miterLimit": 10,
    "startDecorationType": 0
  }
}